xaitoolkit/__init__.py
xaitoolkit/cli.py
xaitoolkit/xai_setup.py
xaitoolkit/loaders/__init__.py
xaitoolkit/loaders/model_loader.py
xaitoolkit/loaders/preprocess.py
xaitoolkit/methods/__init__.py
xaitoolkit/methods/ig.py
xaitoolkit/methods/lime_stratified.py
xaitoolkit/methods/occlusion.py
xaitoolkit/methods/rise.py
xaitoolkit/methods/saliency.py
xaitoolkit/methods/shap_axis_aligned.py
xaitoolkit/methods/smoothgrad.py
xaitoolkit/utils/__init__.py
xaitoolkit/utils/viz.py
xaitoolkit-0.1.1.dist-info/licenses/LICENSE
xaitoolkit-0.1.1.dist-info/METADATA
xaitoolkit-0.1.1.dist-info/WHEEL
xaitoolkit-0.1.1.dist-info/entry_points.txt
xaitoolkit-0.1.1.dist-info/top_level.txt
xaitoolkit-0.1.1.dist-info/RECORD
