Metadata-Version: 2.4
Name: xaitoolkit
Version: 0.1.1
Summary: A lightweight toolkit to explain PyTorch vision models with gradient and perturbation-based XAI.
Author: Muhammad Rashid
License: MIT
Project-URL: Homepage, https://github.com/rashidrao-pk/xaitoolkit
Requires-Python: >=3.8
License-File: LICENSE
Requires-Dist: torch
Requires-Dist: torchvision
Requires-Dist: numpy
Requires-Dist: pillow
Requires-Dist: matplotlib
Requires-Dist: timm
Requires-Dist: scikit-image
Requires-Dist: scikit-learn
Dynamic: license-file
